debug_utility/__init__.py
debug_utility/debug_file.py
debug_utility/utility_file.py
debug_utility-0.4.dist-info/METADATA
debug_utility-0.4.dist-info/WHEEL
debug_utility-0.4.dist-info/top_level.txt
debug_utility-0.4.dist-info/RECORD
