Metadata-Version: 2.1
Name: debug_utility
Version: 0.4
Summary: common functions used while programming in python
Home-page: 
Author: Hien Quoc
Author-email: 
Classifier: Programming Language :: Python :: 3
Classifier: License :: OSI Approved :: MIT License
Classifier: Operating System :: OS Independent
Requires-Python: >=3.10
